{
  "properties": {
    "connectionReferences": {
      "shared_commondataserviceforapps": {
        "runtimeSource": "embedded",
        "connection": {
          "connectionReferenceLogicalName": "ecer_sharedcommondataserviceforapps_8f58e"
        },
        "api": {
          "name": "shared_commondataserviceforapps"
        }
      }
    },
    "definition": {
      "$schema": "https://schema.management.azure.com/providers/Microsoft.Logic/schemas/2016-06-01/workflowdefinition.json#",
      "contentVersion": "1.0.0.0",
      "parameters": {
        "$connections": {
          "defaultValue": {},
          "type": "Object"
        },
        "$authentication": {
          "defaultValue": {},
          "type": "SecureObject"
        }
      },
      "triggers": {
        "When_a_row_is_added,_modified_or_deleted": {
          "metadata": {
            "operationMetadataId": "72266af4-f188-4b90-a9ff-039d61f05555"
          },
          "type": "OpenApiConnectionWebhook",
          "inputs": {
            "host": {
              "connectionName": "shared_commondataserviceforapps",
              "operationId": "SubscribeWebhookTrigger",
              "apiId": "/providers/Microsoft.PowerApps/apis/shared_commondataserviceforapps"
            },
            "parameters": {
              "subscriptionRequest/message": 4,
              "subscriptionRequest/entityname": "ecer_involvedperson",
              "subscriptionRequest/scope": 4,
              "subscriptionRequest/filteringattributes": "ecer_firstname,ecer_lastname"
            },
            "authentication": "@parameters('$authentication')"
          }
        }
      },
      "actions": {
        "Update_Name": {
          "runAfter": {},
          "metadata": {
            "operationMetadataId": "83be39d8-2081-4ea0-8f2a-ba7a703c61e3"
          },
          "type": "OpenApiConnection",
          "inputs": {
            "host": {
              "connectionName": "shared_commondataserviceforapps",
              "operationId": "UpdateRecord",
              "apiId": "/providers/Microsoft.PowerApps/apis/shared_commondataserviceforapps"
            },
            "parameters": {
              "entityName": "ecer_involvedpersons",
              "recordId": "@triggerOutputs()?['body/ecer_involvedpersonid']",
              "item/ecer_name": "@{triggerOutputs()?['body/ecer_firstname']} @{triggerOutputs()?['body/ecer_lastname']}"
            },
            "authentication": "@parameters('$authentication')"
          }
        }
      }
    },
    "templateName": null
  },
  "schemaVersion": "1.0.0.0"
}